promptorium/__init__.py
promptorium/cli.py
promptorium/domain.py
promptorium/services.py
promptorium/data/__init__.py
promptorium/data/wordlist.txt
promptorium/storage/__init__.py
promptorium/storage/base.py
promptorium/storage/fs.py
promptorium/util/__init__.py
promptorium/util/diff.py
promptorium/util/editor.py
promptorium/util/io_safety.py
promptorium/util/keygen.py
promptorium/util/render.py
promptorium/util/repo_root.py
promptorium/py.typed
promptorium_python-0.1.1.dist-info/METADATA
promptorium_python-0.1.1.dist-info/WHEEL
promptorium_python-0.1.1.dist-info/entry_points.txt
promptorium_python-0.1.1.dist-info/licenses/LICENSE
promptorium_python-0.1.1.dist-info/RECORD
