Metadata-Version: 2.4
Name: promptorium-python
Version: 0.1.1
Summary: CLI + library for managing versioned prompts
Project-URL: repository, https://github.com/adambossy/promptorium-python
Author-email: Adam Bossy <adabossy@gmail.com>
License: MIT
License-File: LICENSE
Keywords: ab-testing,ai-prompts,cli,llm-prompts,markdown,prompt-diff,prompt-engineering,prompt-evaluation,prompt-management,prompt-storage,prompt-versioning,prompts,version-control,versioned-prompts
Classifier: Programming Language :: Python :: 3
Classifier: Programming Language :: Python :: 3.12
Classifier: Typing :: Typed
Requires-Python: >=3.12
Requires-Dist: rich>=13.0
Requires-Dist: typer>=0.12
Provides-Extra: dev
Requires-Dist: mypy>=1.10; extra == 'dev'
Requires-Dist: pre-commit>=3.7; extra == 'dev'
Requires-Dist: pytest>=8.0; extra == 'dev'
Requires-Dist: ruff>=0.5.0; extra == 'dev'
